README.md
setup.py
skz_utils/__init__.py
skz_utils/ds_utils.py
skz_utils/im_utils.py
skz_utils/jup_def.py
skz_utils/kd_ocr_tools.py
skz_utils/os_utils.py
skz_utils/pj_utils.py
skz_utils/vi_utils.py
skz_utils/voc_utils.py
skz_utils.egg-info/PKG-INFO
skz_utils.egg-info/SOURCES.txt
skz_utils.egg-info/dependency_links.txt
skz_utils.egg-info/top_level.txt