Metadata-Version: 1.1
Name: skz-utils
Version: 0.1.4
Summary: python utils
Home-page: https://github.com/skyzhao3q/skyz_pyutils.git
Author: zhao-tian
Author-email: skyzhaoi3q@gmail.com
License: MIT
Keywords: some python utils
Platform: UNKNOWN
Classifier: Programming Language :: Python :: 3.0
